iyzipay/__init__.py
iyzipay/iyzipay_resource.py
iyzipay/pki_builder.py
iyzipay-1.0.44.dist-info/LICENSE
iyzipay-1.0.44.dist-info/METADATA
iyzipay-1.0.44.dist-info/WHEEL
iyzipay-1.0.44.dist-info/top_level.txt
iyzipay-1.0.44.dist-info/RECORD
